[
    {
     
"titulo":"Recuerdos de Universidad...1",
"calificacion":"8.1",
"duracion":"2h 21min",
"director":"Joss Whedon",
"estreno":"1 May 2015",
"año": " (2012)",
"imagen":"images/uploads/mv1.jpg",
"estrellas":"Robert Downey Jr.,Chris Evans,  Chris Hemsworth",
"descripcion": "Earth's mightiest heroes must come together and learn to fight as a team if they are to stop the mischievous Loki and his alien army from enslaving humanity... Yolanda"
    },

    {
       
       "titulo": "into the wild",
        "calificacion":"7.8", 
        "duracion":"2h 21min",
        "director":"Anthony Russo,Joe Russo",
        "estreno":"1 May 2015",
        "estrellas":"Chris Evans,Samuel L. Jackson,  Scarlett Johansson",
        "año":" (2014)",
        "imagen":"images/uploads/mv2.jpg",
        "descripcion":"As Steve Rogers struggles to embrace his role in the modern world, he teams up with a  fellow Avenger and S.H.I.E.L.D agent, Black Widow, to battle a new threat... Yolanda"
    
    },
{
  
"titulo":"blade runner",
"calificacion":"7.3",
"duracion":"2h 21min",
"director":"Peyton Reed",
"estreno":"1 May 2015",
"estrellas":"Paul Rudd,Michael Douglas",
"año":" (2015)",
"imagen":"images/uploads/mv3.jpg",
"descripcion":"Armed with a super-suit with the astonishing ability to shrink in scale but increase in strength, cat burglar Scott Lang must embrace his inner hero and help..."




},

{
   
"titulo":"Mulholland pride", 
"calificacion":"7.2",
"duracion":"2h 21min",
"director":"Shane Black",
"estreno":"1 May 2015",
"estrellas":"Robert Downey Jr.,  Guy Pearce,Don Cheadle",
"año":" (2013)" ,
"imagen":"images/uploads/mv4.jpg",
"descripcion":"When Tony Stark's world is torn apart by a formidable terrorist called the Mandarin,  he starts an odyssey of rebuilding and retribution."


},

{
    
"titulo":"skyfall: evil of boss",
"calificacion":"7.0" ,
"duracion":"2h 21min",
"director":"Alan Taylor",
"estreno":"1 May 2015",
"estrellas":"Chris Hemsworth,Natalie Portman,Tom Hiddleston",
"año":" (2014)" ,
"imagen":"images/uploads/mv5.jpg",
"descripcion":"When Tony Stark's world is torn apart by a formidable terrorist called the Mandarin he starts an odyssey of rebuilding and retribution."



},

{
     
    "titulo":"Recuerdos de Universidad.....2",
    "calificacion":"8.1",
    "duracion":"2h 21min",
    "director":"Joss Whedon",
    "estreno":"1 May 2015",
    "año": " (2012)",
    "imagen":"images/uploads/mv1.jpg",
    "estrellas":"Robert Downey Jr.,Chris Evans,  Chris Hemsworth",
    "descripcion": "Earth's mightiest heroes must come together and learn to fight as a team if they are to stop the mischievous Loki and his alien army from enslaving humanity... Yolanda"
        },
    
        {
           
           "titulo": "into the wild",
            "calificacion":"7.8", 
            "duracion":"2h 21min",
            "director":"Anthony Russo,Joe Russo",
            "estreno":"1 May 2015",
            "estrellas":"Chris Evans,Samuel L. Jackson,  Scarlett Johansson",
            "año":" (2014)",
            "imagen":"images/uploads/mv2.jpg",
            "descripcion":"As Steve Rogers struggles to embrace his role in the modern world, he teams up with a  fellow Avenger and S.H.I.E.L.D agent, Black Widow, to battle a new threat... Yolanda"
        
        },
    {
      
    "titulo":"blade runner",
    "calificacion":"7.3",
    "duracion":"2h 21min",
    "director":"Peyton Reed",
    "estreno":"1 May 2015",
    "estrellas":"Paul Rudd,Michael Douglas",
    "año":" (2015)",
    "imagen":"images/uploads/mv3.jpg",
    "descripcion":"Armed with a super-suit with the astonishing ability to shrink in scale but increase in strength, cat burglar Scott Lang must embrace his inner hero and help..."
    
    
    
    
    },
    
    {
       
    "titulo":"Mulholland pride", 
    "calificacion":"7.2",
    "duracion":"2h 21min",
    "director":"Shane Black",
    "estreno":"1 May 2015",
    "estrellas":"Robert Downey Jr.,  Guy Pearce,Don Cheadle",
    "año":" (2013)" ,
    "imagen":"images/uploads/mv4.jpg",
    "descripcion":"When Tony Stark's world is torn apart by a formidable terrorist called the Mandarin,  he starts an odyssey of rebuilding and retribution."
    
    
    },
    
    {
        
    "titulo":"skyfall: evil of boss",
    "calificacion":"7.0" ,
    "duracion":"2h 21min",
    "director":"Alan Taylor",
    "estreno":"1 May 2015",
    "estrellas":"Chris Hemsworth,Natalie Portman,Tom Hiddleston",
    "año":" (2014)" ,
    "imagen":"images/uploads/mv5.jpg",
    "descripcion":"When Tony Stark's world is torn apart by a formidable terrorist called the Mandarin he starts an odyssey of rebuilding and retribution."
    
    
    
    },

    {
     
        "titulo":"Recuerdos de Universidad....3",
        "calificacion":"8.1",
        "duracion":"2h 21min",
        "director":"Joss Whedon",
        "estreno":"1 May 2015",
        "año": " (2012)",
        "imagen":"images/uploads/mv1.jpg",
        "estrellas":"Robert Downey Jr.,Chris Evans,  Chris Hemsworth",
        "descripcion": "Earth's mightiest heroes must come together and learn to fight as a team if they are to stop the mischievous Loki and his alien army from enslaving humanity... Yolanda"
            },
        
            {
               
               "titulo": "into the wild",
                "calificacion":"7.8", 
                "duracion":"2h 21min",
                "director":"Anthony Russo,Joe Russo",
                "estreno":"1 May 2015",
                "estrellas":"Chris Evans,Samuel L. Jackson,  Scarlett Johansson",
                "año":" (2014)",
                "imagen":"images/uploads/mv2.jpg",
                "descripcion":"As Steve Rogers struggles to embrace his role in the modern world, he teams up with a  fellow Avenger and S.H.I.E.L.D agent, Black Widow, to battle a new threat... Yolanda"
            
            },
        {
          
        "titulo":"blade runner",
        "calificacion":"7.3",
        "duracion":"2h 21min",
        "director":"Peyton Reed",
        "estreno":"1 May 2015",
        "estrellas":"Paul Rudd,Michael Douglas",
        "año":" (2015)",
        "imagen":"images/uploads/mv3.jpg",
        "descripcion":"Armed with a super-suit with the astonishing ability to shrink in scale but increase in strength, cat burglar Scott Lang must embrace his inner hero and help..."
        
        
        
        
        },
        
        {
           
        "titulo":"Mulholland pride", 
        "calificacion":"7.2",
        "duracion":"2h 21min",
        "director":"Shane Black",
        "estreno":"1 May 2015",
        "estrellas":"Robert Downey Jr.,  Guy Pearce,Don Cheadle",
        "año":" (2013)" ,
        "imagen":"images/uploads/mv4.jpg",
        "descripcion":"When Tony Stark's world is torn apart by a formidable terrorist called the Mandarin,  he starts an odyssey of rebuilding and retribution."
        
        
        },
        
        {
            
        "titulo":"skyfall: evil of boss",
        "calificacion":"7.0" ,
        "duracion":"2h 21min",
        "director":"Alan Taylor",
        "estreno":"1 May 2015",
        "estrellas":"Chris Hemsworth,Natalie Portman,Tom Hiddleston",
        "año":" (2014)" ,
        "imagen":"images/uploads/mv5.jpg",
        "descripcion":"When Tony Stark's world is torn apart by a formidable terrorist called the Mandarin he starts an odyssey of rebuilding and retribution."
        
        
        
        },

        {
     
            "titulo":"Recuerdos de Universidad...4",
            "calificacion":"8.1",
            "duracion":"2h 21min",
            "director":"Joss Whedon",
            "estreno":"1 May 2015",
            "año": " (2012)",
            "imagen":"images/uploads/mv1.jpg",
            "estrellas":"Robert Downey Jr.,Chris Evans,  Chris Hemsworth",
            "descripcion": "Earth's mightiest heroes must come together and learn to fight as a team if they are to stop the mischievous Loki and his alien army from enslaving humanity... Yolanda"
                },
            
                {
                   
                   "titulo": "into the wild",
                    "calificacion":"7.8", 
                    "duracion":"2h 21min",
                    "director":"Anthony Russo,Joe Russo",
                    "estreno":"1 May 2015",
                    "estrellas":"Chris Evans,Samuel L. Jackson,  Scarlett Johansson",
                    "año":" (2014)",
                    "imagen":"images/uploads/mv2.jpg",
                    "descripcion":"As Steve Rogers struggles to embrace his role in the modern world, he teams up with a  fellow Avenger and S.H.I.E.L.D agent, Black Widow, to battle a new threat... Yolanda"
                
                },
            {
              
            "titulo":"blade runner",
            "calificacion":"7.3",
            "duracion":"2h 21min",
            "director":"Peyton Reed",
            "estreno":"1 May 2015",
            "estrellas":"Paul Rudd,Michael Douglas",
            "año":" (2015)",
            "imagen":"images/uploads/mv3.jpg",
            "descripcion":"Armed with a super-suit with the astonishing ability to shrink in scale but increase in strength, cat burglar Scott Lang must embrace his inner hero and help..."
            
            
            
            
            },
            
            {
               
            "titulo":"Mulholland pride", 
            "calificacion":"7.2",
            "duracion":"2h 21min",
            "director":"Shane Black",
            "estreno":"1 May 2015",
            "estrellas":"Robert Downey Jr.,  Guy Pearce,Don Cheadle",
            "año":" (2013)" ,
            "imagen":"images/uploads/mv4.jpg",
            "descripcion":"When Tony Stark's world is torn apart by a formidable terrorist called the Mandarin,  he starts an odyssey of rebuilding and retribution."
            
            
            },
            
            {
                
            "titulo":"skyfall: evil of boss",
            "calificacion":"7.0" ,
            "duracion":"2h 21min",
            "director":"Alan Taylor",
            "estreno":"1 May 2015",
            "estrellas":"Chris Hemsworth,Natalie Portman,Tom Hiddleston",
            "año":" (2014)" ,
            "imagen":"images/uploads/mv5.jpg",
            "descripcion":"When Tony Stark's world is torn apart by a formidable terrorist called the Mandarin he starts an odyssey of rebuilding and retribution."
            
            
            
            }
            
        
    




]